{"title":"Combined feed","url":"https://LIVESTREAM-KR.github.io/navertv_music_stage/all.xml","elements":[{"title":"살짝 설렜어 (Nonstop) - 오마이걸(OH MY GIRL) (KBS 뮤직뱅크 ─ 네이버TV)","contents":"3:32","link":"https://tv.naver.com/v/13816318","retrieved":1663770505994,"image":"https://phinf.pstatic.net/tvcast/20200515_98/LTJcf_1589536302737cNa4A_PNG/2b329870fc1ecf4a03f88fb80f881c73.png?type=f194_109_blend"},{"title":"[Hot Debut] 케이팝의 신! 장르는 '기팝', 기현 (몬스타엑스) 'VOYAGER' (SBS MTV 더쇼 ─ 네이버TV)","contents":"3:28","link":"https://tv.naver.com/v/25791858","retrieved":1665429967367,"image":"https://phinf.pstatic.net/tvcast/20220322_90/bGgbw_1647946025153oz52n_JPEG/xBy1647944938111-1280-0.jpg?type=f194_109_blend"},{"title":"오늘의 더 쇼 초이스는? (SBS MTV 더쇼 ─ 네이버TV)","contents":"3:50","link":"https://tv.naver.com/v/25791857","retrieved":1665429967370,"image":"https://phinf.pstatic.net/tvcast/20220322_128/rxNKh_1647946023304qFU5f_JPEG/6UP1647944930693-1280-0.jpg?type=f194_109_blend"},{"title":"[Comeback] 봄을 알리는 활기찬 꿀 보이스, 솔라(Solar) '꿀 (HONEY)' (SBS MTV 더쇼 ─ 네이버TV)","contents":"2:59","link":"https://tv.naver.com/v/25791694","retrieved":1665429967371,"image":"https://phinf.pstatic.net/tvcast/20220322_65/4REyC_1647945490175Kv2Bb_JPEG/jwe1647944877132-1280-0.jpg?type=f194_109_blend"},{"title":"[Comeback] 몽환적 퍼포먼스 속으로, 문빈&산하(ASTRO) 'WHO' (SBS MTV 더쇼 ─ 네이버TV)","contents":"3:12","link":"https://tv.naver.com/v/25791599","retrieved":1665429967373,"image":"https://phinf.pstatic.net/tvcast/20220322_299/lH8IA_1647945126810Enieq_JPEG/vY21647944276962-1280-0.jpg?type=f194_109_blend"},{"title":"[Comeback] 독보적 당당함으로 돌아온, (여자)아이들 'TOMBOY' (SBS MTV 더쇼 ─ 네이버TV)","contents":"3:05","link":"https://tv.naver.com/v/25791593","retrieved":1665429967373,"image":"https://phinf.pstatic.net/tvcast/20220322_300/RZ8ps_1647945123215cr3e5_JPEG/oM71647944190242-1280-0.jpg?type=f194_109_blend"},{"title":"러블리 다채로운 매력, 체리블렛 (Cherry Bullet) 'Love In Space' (SBS MTV 더쇼 ─ 네이버TV)","contents":"3:43","link":"https://tv.naver.com/v/25791503","retrieved":1665429967377,"image":"https://phinf.pstatic.net/tvcast/20220322_94/ic2Us_1647944824833n6kG0_JPEG/x821647943950922-1280-0.jpg?type=f194_109_blend"},{"title":"[Comeback] 싱그러운 청춘의 아이콘, 위아이(WEi) 'Too Bad' (SBS MTV 더쇼 ─ 네이버TV)","contents":"3:47","link":"https://tv.naver.com/v/25791501","retrieved":1665429967382,"image":"https://phinf.pstatic.net/tvcast/20220322_205/zjE9w_1647944822221sBEii_JPEG/c0b1647943816519-1280-0.jpg?type=f194_109_blend"},{"title":"파워풀 사운드 퍼포먼스, 위아이(WEi) 'Super Bumpy' (SBS MTV 더쇼 ─ 네이버TV)","contents":"3:26","link":"https://tv.naver.com/v/25791500","retrieved":1665429967382,"image":"https://phinf.pstatic.net/tvcast/20220322_50/t8ZwI_1647944820327LsD1X_JPEG/TZS1647943784527-1280-0.jpg?type=f194_109_blend"},{"title":"무대 위 솔직한 매력이 돋보이는, 로켓펀치(Rocket Punch) 'CHIQUITA' (SBS MTV 더쇼 ─ 네이버TV)","contents":"3:11","link":"https://tv.naver.com/v/25791326","retrieved":1665429967382,"image":"https://phinf.pstatic.net/tvcast/20220322_205/kH0ES_1647944232137Ud6eL_JPEG/iRF1647943396181-1280-0.jpg?type=f194_109_blend"},{"title":"[THE 미니웨이] 문빈&산하(ASTRO) (SBS MTV 더쇼 ─ 네이버TV)","contents":"3:38","link":"https://tv.naver.com/v/25791323","retrieved":1665429967384,"image":"https://phinf.pstatic.net/tvcast/20220322_132/vn6ZB_16479442282735jH1z_JPEG/88y1647943205935-1280-0.jpg?type=f194_109_blend"},{"title":"유니크한 무대부터 다채로운 표정까지!, Billlie 'GingaMingaYo (the strange world)' (SBS MTV 더쇼 ─ 네이버TV)","contents":"3:38","link":"https://tv.naver.com/v/25791321","retrieved":1665429967385,"image":"https://phinf.pstatic.net/tvcast/20220322_193/zvOqT_1647944226060gNgAt_JPEG/y4V1647943187259-1280-0.jpg?type=f194_109_blend"},{"title":"중독성 있는 멜로디, 남승민 '바보같은 사람' (SBS MTV 더쇼 ─ 네이버TV)","contents":"3:37","link":"https://tv.naver.com/v/25791117","retrieved":1665429967385,"image":"https://phinf.pstatic.net/tvcast/20220322_42/AqggC_1647943620984epW8n_JPEG/hDr1647942521249-1280-0.jpg?type=f194_109_blend"},{"title":"[모두의 엔딩 - 쇼랑해] 위아이(WEi) (SBS MTV 더쇼 ─ 네이버TV)","contents":"3:25","link":"https://tv.naver.com/v/25791017","retrieved":1665429967387,"image":"https://phinf.pstatic.net/tvcast/20220322_206/KuEim_1647943327366cVIo1_JPEG/pLN1647942387404-1280-0.jpg?type=f194_109_blend"},{"title":"청량 가득 밝은 에너지, TEMPEST (템페스트) 'Bad News' (SBS MTV 더쇼 ─ 네이버TV)","contents":"3:38","link":"https://tv.naver.com/v/25791015","retrieved":1665429967388,"image":"https://phinf.pstatic.net/tvcast/20220322_123/rd9SA_1647943325353UovuG_JPEG/lZS1647942370955-1280-0.jpg?type=f194_109_blend"},{"title":"이별을 이야기하는, 류정운 '비구름' (SBS MTV 더쇼 ─ 네이버TV)","contents":"3:30","link":"https://tv.naver.com/v/25791011","retrieved":1665429967388,"image":"https://phinf.pstatic.net/tvcast/20220322_287/n3UNt_1647943321136uQRQD_JPEG/PGq1647942235677-1280-0.jpg?type=f194_109_blend"},{"title":"심장도 춤추는 매력적 리듬, TAN 'DU DU DU' (SBS MTV 더쇼 ─ 네이버TV)","contents":"3:37","link":"https://tv.naver.com/v/25790858","retrieved":1665429967390,"image":"https://phinf.pstatic.net/tvcast/20220322_79/ZVQMW_1647942784417ws4ni_JPEG/eDq1647941606912-1280-0.jpg?type=f194_109_blend"},{"title":"따뜻한 메시지를 전하는, LUMIN(루민) '너를 담다' (SBS MTV 더쇼 ─ 네이버TV)","contents":"2:55","link":"https://tv.naver.com/v/25790755","retrieved":1665429967392,"image":"https://phinf.pstatic.net/tvcast/20220322_50/hhBh0_1647942426328TDrr7_JPEG/ZV91647941496174-1280-0.jpg?type=f194_109_blend"},{"title":"거침없이 나아가는, CRAXY (크랙시) 'Trigger' (SBS MTV 더쇼 ─ 네이버TV)","contents":"3:10","link":"https://tv.naver.com/v/25790467","retrieved":1665429967394,"image":"https://phinf.pstatic.net/tvcast/20220322_265/FHjiJ_1647941521594xA8Ve_JPEG/Hq01647940465987-1280-0.jpg?type=f194_109_blend"},{"title":"7월 11일 더쇼 초이스! 영광의 주인공은? (SBS MTV 더쇼 ─ 네이버TV)","contents":"3:32","link":"https://tv.naver.com/v/1850764","retrieved":1665429967395,"image":"https://phinf.pstatic.net/tvcast/20170727_53/TBeuU_1501119669972etI4a_JPEG/VD58947719_w1279.jpg?type=f194_109_blend"},{"title":"귀도 마음도 힐링 시키는 신이 내린 목소리 김태우 '따라가' (SBS MTV 더쇼 ─ 네이버TV)","contents":"3:30","link":"https://tv.naver.com/v/1850692","retrieved":1665429967397,"image":"https://phinf.pstatic.net/tvcast/20170727_265/FJDTp_1501119668219TLSWG_JPEG/VD68149475_w1279.jpg?type=f194_109_blend"},{"title":"누가 섹시함을 묻거든 이 무대를 보여주도록! 나인뮤지스 '기억해' (SBS MTV 더쇼 ─ 네이버TV)","contents":"3:43","link":"https://tv.naver.com/v/1850653","retrieved":1665429967400,"image":"https://phinf.pstatic.net/tvcast/20170727_46/cqWk2_1501119667421DqAvf_JPEG/VD74137377_w1279.jpg?type=f194_109_blend"},{"title":"이 무대 자꾸 보고싶은 이유는~? 마마무 '나로 말할 것 같으면' (SBS MTV 더쇼 ─ 네이버TV)","contents":"3:33","link":"https://tv.naver.com/v/1850637","retrieved":1665429967402,"image":"https://phinf.pstatic.net/tvcast/20170727_264/iNKbo_1501119658107TyFKi_JPEG/VD38070771_w1279.jpg?type=f194_109_blend"},{"title":"맨발 퍼포먼스로 표현하는 몽환섹시! 스텔라 '세피로트의 나무' (SBS MTV 더쇼 ─ 네이버TV)","contents":"3:05","link":"https://tv.naver.com/v/1850603","retrieved":1665429967403,"image":"https://phinf.pstatic.net/tvcast/20170727_185/X4YyR_1501119657338qa3N8_JPEG/VD61250621_w1279.jpg?type=f194_109_blend"},{"title":"키워드로 알아보는 2017 하반기 가요계 소식 '더쇼 뉴스 2부' (SBS MTV 더쇼 ─ 네이버TV)","contents":"3:41","link":"https://tv.naver.com/v/1850560","retrieved":1665429967405,"image":"https://phinf.pstatic.net/tvcast/20170727_192/GYkBu_1501119656533st1X0_JPEG/VD94864836_w1279.jpg?type=f194_109_blend"},{"title":"상남자 매력이 뭔지 궁금하다면 여기여기! 헤일로 '여기여기' (SBS MTV 더쇼 ─ 네이버TV)","contents":"3:08","link":"https://tv.naver.com/v/1850559","retrieved":1665429967421,"image":"https://phinf.pstatic.net/tvcast/20170727_7/6U1eQ_1501119655719Crfcd_JPEG/VD38776230_w1279.jpg?type=f194_109_blend"},{"title":"아련한 이 남자들에게 빠질까 봐 겁이 나 헤일로 '겁이 나' (SBS MTV 더쇼 ─ 네이버TV)","contents":"2:30","link":"https://tv.naver.com/v/1850499","retrieved":1665429967421,"image":"https://phinf.pstatic.net/tvcast/20170727_279/SB79M_1501119654831juVEJ_JPEG/VD80072710_w1279.jpg?type=f194_109_blend"},{"title":"올 여름을 빨~갛게 물들일 중독적인 맛! Comeback 레드벨벳 '빨간 맛' (SBS MTV 더쇼 ─ 네이버TV)","contents":"3:19","link":"https://tv.naver.com/v/1850493","retrieved":1665429967422,"image":"https://phinf.pstatic.net/tvcast/20170727_3/DITrZ_1501119652686Ah7Uz_JPEG/VD35740232_w1279.jpg?type=f194_109_blend"},{"title":"박력 남자들의 카리스마 무대 지금 시작해! 업텐션 '시작해' (SBS MTV 더쇼 ─ 네이버TV)","contents":"3:20","link":"https://tv.naver.com/v/1850487","retrieved":1665429967423,"image":"https://phinf.pstatic.net/tvcast/20170727_129/K9r2k_1501119085270loUOs_JPEG/VD42314271_w1279.jpg?type=f194_109_blend"},{"title":"로맨스 영화보다 더 달달한 케미스트리! 앤씨아 (feat. 제율) '읽어주세요' (SBS MTV 더쇼 ─ 네이버TV)","contents":"3:50","link":"https://tv.naver.com/v/1850455","retrieved":1665429967427,"image":"https://phinf.pstatic.net/tvcast/20170727_30/lfCoo_15011190809017ifvV_JPEG/VD89720958_w1279.jpg?type=f194_109_blend"},{"title":"눈물 주의보! 눈도 마음도 촉촉해지는 박재정 '시력' (SBS MTV 더쇼 ─ 네이버TV)","contents":"3:01","link":"https://tv.naver.com/v/1850421","retrieved":1665429967429,"image":"https://phinf.pstatic.net/tvcast/20170727_192/1wlTn_15011190800075vXzH_JPEG/VD96897571_w1279.jpg?type=f194_109_blend"}]}