{"title":"MBC M 쇼챔피언 ─ 네이버TV","url":"https://tv.naver.com/showchampion/clips","favicon":"https://tv.naver.com/showchampion/favicon.ico","elements":[{"title":"[COMEBACK] OH MY GIRL - Real Love (오마이걸 - 리얼 러브)","contents":"3:56","link":"https://tv.naver.com/v/26076664","retrieved":1649243714822,"image":"https://phinf.pstatic.net/tvcast/20220406_67/ht1HA_1649241424834cGxKh_JPEG/CA202204060064.jpg?type=f194_109_blend"},{"title":"[COMEBACK] OH MY GIRL - Drip (오마이걸 - 드립)","contents":"3:32","link":"https://tv.naver.com/v/26076504","retrieved":1649243714823,"image":"https://phinf.pstatic.net/tvcast/20220406_108/Pr21s_16492411294379Y0j6_JPEG/CA202204060063.jpg?type=f194_109_blend"},{"title":"[COMEBACK] VERIVERY - O (베리베리 - 오)","contents":"3:40","link":"https://tv.naver.com/v/26076227","retrieved":1649243714825,"image":"https://phinf.pstatic.net/tvcast/20220406_130/nPhyC_1649240584702PJf6U_JPEG/CA202204060062.jpg?type=f194_109_blend"},{"title":"CRAVITY - Adrenaline (크래비티 - 아드레날린)","contents":"3:39","link":"https://tv.naver.com/v/26076192","retrieved":1649243714827,"image":"https://phinf.pstatic.net/tvcast/20220406_152/OPtqc_1649240520784Mooyh_JPEG/CA202204060061.jpg?type=f194_109_blend"},{"title":"하이틴 남주가 될 CRAVITY 3대 엔딩 요정은?","contents":"4:05","link":"https://tv.naver.com/v/26076041","retrieved":1649240400318,"image":"https://phinf.pstatic.net/tvcast/20220406_182/Cm8Gi_16492402242203Whqg_JPEG/CA202204060060.jpg?type=f194_109_blend"},{"title":"[최초 공개] PURPLE KISS - Intro : Illusion+memeM (퍼플키스 - 인트로 : 일루션+맴맴)","contents":"4:18","link":"https://tv.naver.com/v/26076039","retrieved":1649240400340,"image":"https://phinf.pstatic.net/tvcast/20220406_69/SosaG_1649240222155V8kII_JPEG/CA202204060059.jpg?type=f194_109_blend"},{"title":"LIM SANG HYUN -  Honey Milk Tea (임상현 - 달콤하게, 따뜻하게, 부드럽게)","contents":"3:20","link":"https://tv.naver.com/v/26075753","retrieved":1649240400340,"image":"https://phinf.pstatic.net/tvcast/20220406_14/heUc7_1649239624434UU18v_JPEG/CA202204060058.jpg?type=f194_109_blend"},{"title":"KINGDOM - Ascension (킹덤 - 승천)","contents":"3:41","link":"https://tv.naver.com/v/26075614","retrieved":1649240400341,"image":"https://phinf.pstatic.net/tvcast/20220406_145/2M7G1_1649239322871sSbwP_JPEG/CA202204060056.jpg?type=f194_109_blend"},{"title":"'찾았다~ Real Love!' 오마이걸 엔딩 요정은?","contents":"4:13","link":"https://tv.naver.com/v/26075363","retrieved":1649240400341,"image":"https://phinf.pstatic.net/tvcast/20220406_79/iDput_1649238784936bJj3K_JPEG/CA202204060054.jpg?type=f194_109_blend"},{"title":"Swan - Sometimes (수안 - 어떤 날에는)","contents":"3:27","link":"https://tv.naver.com/v/26075328","retrieved":1649240400341,"image":"https://phinf.pstatic.net/tvcast/20220406_55/wdDNE_16492387196164mSkH_JPEG/CA202204060053.jpg?type=f194_109_blend"},{"title":"D-CRUNCH - Addiction (디크런치 - 중독)","contents":"3:23","link":"https://tv.naver.com/v/26075175","retrieved":1649240400342,"image":"https://phinf.pstatic.net/tvcast/20220406_127/Dyeuu_1649238430014xCf5i_JPEG/CA202204060052.jpg?type=f194_109_blend"},{"title":"[HOT DEBUT] NINE.i - Parallel Universe (나인아이 - 페러렐 유니버스)","contents":"3:40","link":"https://tv.naver.com/v/26075168","retrieved":1649240400342,"image":"https://phinf.pstatic.net/tvcast/20220406_298/o87Me_1649238423956E7sj3_JPEG/CA202204060051.jpg?type=f194_109_blend"},{"title":"[HOT DEBUT] ILY:1 - Love In Bloom (아일리원 - 사랑아 피어라)","contents":"3:16","link":"https://tv.naver.com/v/26075166","retrieved":1649240400342,"image":"https://phinf.pstatic.net/tvcast/20220406_173/wweHu_1649238421941Yanzn_JPEG/CA202204060050.jpg?type=f194_109_blend"},{"title":"[줍줍 TIME] 베러들을 위한 VERIVERY의 청순섹시 줍줍 TIME♥","contents":"3:06","link":"https://tv.naver.com/v/26074868","retrieved":1649240400342,"image":"https://phinf.pstatic.net/tvcast/20220406_233/pUqFq_1649237879650PkJT3_JPEG/CA202204060049.jpg?type=f194_109_blend"},{"title":"MAJORS - Salute (메이져스 - 설루트)","contents":"3:09","link":"https://tv.naver.com/v/26074831","retrieved":1649240400343,"image":"https://phinf.pstatic.net/tvcast/20220406_94/1ldkc_1649237825117fc6xb_JPEG/CA202204060048.jpg?type=f194_109_blend"},{"title":"DO JIN LEE - If you are coming back to me again… (이도진 - 그대 내게 다시 올까요)","contents":"3:33","link":"https://tv.naver.com/v/26074665","retrieved":1649240400376,"image":"https://phinf.pstatic.net/tvcast/20220406_253/Ut8l1_1649237521914vTO9P_JPEG/CA202204060047.jpg?type=f194_109_blend"},{"title":"PRITTI-G - Let Me Out (프리티지 - 렛 미 아웃)","contents":"3:02","link":"https://tv.naver.com/v/26074435","retrieved":1649240400377,"image":"https://phinf.pstatic.net/tvcast/20220406_140/Ynb49_1649236980860zaEHa_JPEG/CA202204060046.jpg?type=f194_109_blend"},{"title":"[예고] 사랑을 이루어 드립니다! 크래비티 ♡연애 조작단♡을 찾아온 의뢰인.. 과연 그 결과는?!","contents":"1:44","link":"https://tv.naver.com/v/26022790","retrieved":1649049384415,"image":"https://phinf.pstatic.net/tvcast/20220404_19/ZsU1U_1649048887128mt2Nb_JPEG/CA202204060003.jpg?type=f194_109_blend"},{"title":"3월 5주차 ♥쇼챔피언♡ MC 모음.zip (베리베리 강민, 아스트로 문빈&산하) | Show Champion | EP.428","contents":"6:57","link":"https://tv.naver.com/v/25960431","retrieved":1648898054810,"image":"https://phinf.pstatic.net/tvcast/20220331_2/jyEKS_1648716783671bed1y_JPEG/CA202203300120.jpg?type=f194_109_blend"},{"title":"[쇼챔 1위] 3월 다섯째 주 챔피언송 Stray Kids 앵콜 Full ver.","contents":"4:44","link":"https://tv.naver.com/v/25943939","retrieved":1648643414307,"image":"https://phinf.pstatic.net/tvcast/20220330_141/t5Akx_1648641725448XstnO_JPEG/CA202203300106.jpg?type=f194_109_blend"},{"title":"D-CRUNCH - Addiction (디크런치 - 중독)","contents":"3:23","link":"https://tv.naver.com/v/25943797","retrieved":1648643414308,"image":"https://phinf.pstatic.net/tvcast/20220330_204/smpAB_1648641206568Mr1Oy_JPEG/CA202203300100.jpg?type=f194_109_blend"},{"title":"[쇼챔직캠] CRAVITY SERIM - Adrenaline (크래비티 세림 - 아드레날린) | Show Champion | EP.428","contents":"3:27","link":"https://tv.naver.com/v/25943132","retrieved":1648646848423,"image":"https://phinf.pstatic.net/tvcast/20220330_177/IRtzy_1648639020530AzWF0_JPEG/CA202203300082.jpg?type=f194_109_blend"},{"title":"[쇼챔직캠] CRAVITY WONJIN - Adrenaline (크래비티 원진 - 아드레날린) | Show Champion | EP.428","contents":"3:27","link":"https://tv.naver.com/v/25942976","retrieved":1648646848424,"image":"https://phinf.pstatic.net/tvcast/20220330_15/1nvLz_1648638420415VIUov_JPEG/CA202203300084.jpg?type=f194_109_blend"},{"title":"[쇼챔직캠] Billlie TSUKI - a sign ~ anonymous (빌리 츠키 - 어 사인 ~ 어노니머스) | Show Champion | EP.428","contents":"3:15","link":"https://tv.naver.com/v/25942762","retrieved":1648646848426,"image":"https://phinf.pstatic.net/tvcast/20220330_13/2w4Eh_1648637825015ureRe_JPEG/CA202203300081.jpg?type=f194_109_blend"},{"title":"[COMEBACK] Highlight - Night Fog (하이라이트 - 밤안개)","contents":"2:40","link":"https://tv.naver.com/v/25942603","retrieved":1648638866491,"image":"https://phinf.pstatic.net/tvcast/20220330_284/GEzCW_1648637232351X7fdj_JPEG/CA202203300080.jpg?type=f194_109_blend"},{"title":"[쇼챔직캠] CRAVITY JUNGMO - Adrenaline (크래비티 정모 - 아드레날린) | Show Champion | EP.428","contents":"3:27","link":"https://tv.naver.com/v/25942602","retrieved":1648646848429,"image":"https://phinf.pstatic.net/tvcast/20220330_177/ehuoJ_1648637229470cafAz_JPEG/CA202203300085.jpg?type=f194_109_blend"},{"title":"[쇼챔직캠] Brave Girls EUNJI - Thank You (브레이브걸스 은지 - 땡큐) l Show Champion l EP.428","contents":"3:16","link":"https://tv.naver.com/v/25942596","retrieved":1648646848430,"image":"https://phinf.pstatic.net/tvcast/20220330_133/6mZFz_16486372226494JaVP_JPEG/CA202203300071.jpg?type=f194_109_blend"},{"title":"[쇼챔직캠] CRAVITY HYEONGJUN - Adrenaline (크래비티 형준 - 아드레날린) | Show Champion | EP.428","contents":"3:27","link":"https://tv.naver.com/v/25942595","retrieved":1648646848431,"image":"https://phinf.pstatic.net/tvcast/20220330_124/LxpHx_1648637221344E6j0P_JPEG/CA202203300086.jpg?type=f194_109_blend"},{"title":"[쇼챔직캠] Brave Girls YUJEONG - Thank You (브레이브걸스 유정 - 땡큐) l Show Champion l EP.428","contents":"3:16","link":"https://tv.naver.com/v/25942527","retrieved":1648646848432,"image":"https://phinf.pstatic.net/tvcast/20220330_85/fFhEg_1648636930538KdHk9_JPEG/CA202203300070.jpg?type=f194_109_blend"},{"title":"[쇼챔직캠 4K] Billlie SHEON - a sign ~ anonymous (빌리 션 - 어 사인 ~ 어노니머스) | Show Champion | EP.428","contents":"3:15","link":"https://tv.naver.com/v/25942525","retrieved":1648646848433,"image":"https://phinf.pstatic.net/tvcast/20220330_16/3OQLw_1648636929175cAntC_JPEG/CA202203300077.jpg?type=f194_109_blend"}]}