{"title":"MBC 쇼! 음악중심 ─ 네이버TV","url":"https://tv.naver.com/musiccore/clips","favicon":"https://tv.naver.com/musiccore/favicon.ico","elements":[{"title":"[#최애직캠] aespa NINGNING - Drama(에스파 닝닝 - 드라마) Close-up Cam | Show! MusicCore | MBC231111방송","contents":"3:55","link":"https://tv.naver.com/v/42769240","retrieved":1699870497931,"image":"https://phinf.pstatic.net/tvcast/20231113_76/dzKhe_1699868202737Shcem_JPEG/clip_20231113174938_17.jpg?type=f194_109_blend"},{"title":"[#최애직캠] aespa WINTER - Drama(에스파 윈터 - 드라마) Close-up Cam | Show! MusicCore | MBC231111방송","contents":"4:07","link":"https://tv.naver.com/v/42769235","retrieved":1699870497931,"image":"https://phinf.pstatic.net/tvcast/20231113_240/cTFfV_1699868200980tjfgP_JPEG/clip_20231113174925_16.jpg?type=f194_109_blend"},{"title":"[#최애직캠] aespa GISELLE - Drama(에스파 지젤 - 드라마) Close-up Cam | Show! MusicCore | MBC231111방송","contents":"4:09","link":"https://tv.naver.com/v/42769229","retrieved":1699870497932,"image":"https://phinf.pstatic.net/tvcast/20231113_116/rmoeI_16998681987864Iebv_PNG/clip_20231113174919_15.png?type=f194_109_blend"},{"title":"[#최애직캠] aespa KARINA - Drama(에스파 카리나 - 드라마) Close-up Cam | Show! MusicCore | MBC231111방송","contents":"4:07","link":"https://tv.naver.com/v/42769226","retrieved":1699870497932,"image":"https://phinf.pstatic.net/tvcast/20231113_15/wr6FM_1699868196729wTgwh_JPEG/clip_20231113174914_14.jpg?type=f194_109_blend"},{"title":"[#최애직캠] ZEROBASEONE HAN YU JIN - CRUSH(제로베이스원 한유진 - 가시) Close-up Cam | Show! MusicCore | MBC231111방","contents":"3:36","link":"https://tv.naver.com/v/42767623","retrieved":1699866865918,"image":"https://phinf.pstatic.net/tvcast/20231113_108/K5n8h_1699866694027gOXaA_JPEG/clip_20231113164317_27.jpg?type=f194_109_blend"},{"title":"[#최애직캠] ZEROBASEONE KIM GYU VIN - CRUSH(제로베이스원 김규빈 - 가시) Close-up Cam | Show! MusicCore|MBC231111방송","contents":"3:22","link":"https://tv.naver.com/v/42767619","retrieved":1699866865920,"image":"https://phinf.pstatic.net/tvcast/20231113_55/pexr9_16998666918047pvu9_JPEG/clip_20231113164310_26.jpg?type=f194_109_blend"},{"title":"[#최애직캠] ZEROBASEONE Zhang Hao - CRUSH(제로베이스원 장하오 - 가시) Close-up Cam | Show! MusicCore | MBC231111방송","contents":"3:27","link":"https://tv.naver.com/v/42767617","retrieved":1699866865922,"image":"https://phinf.pstatic.net/tvcast/20231113_246/vX6V2_1699866690139xMdKe_JPEG/clip_20231113164247_24.jpg?type=f194_109_blend"},{"title":"[#최애직캠] ZEROBASEONE RICKY - CRUSH(제로베이스원 리키 - 가시) Close-up Cam | Show! MusicCore | MBC231111방송","contents":"3:24","link":"https://tv.naver.com/v/42767278","retrieved":1699866865925,"image":"https://phinf.pstatic.net/tvcast/20231113_297/jp6RE_1699866399745nhXhW_JPEG/clip_20231113164300_25.jpg?type=f194_109_blend"},{"title":"[#최애직캠] ZEROBASEONE SUNG HAN BIN - CRUSH(제로베이스원 성한빈 - 가시) Close-up Cam | Show! MusicCore|MBC231111방","contents":"3:20","link":"https://tv.naver.com/v/42767277","retrieved":1699866865928,"image":"https://phinf.pstatic.net/tvcast/20231113_24/zdl5z_1699866397802fn5CH_JPEG/clip_20231113164241_23.jpg?type=f194_109_blend"},{"title":"[#최애직캠] Stray Kids HYUNJIN - LALALALA(스트레이 키즈 현진 - 락(樂)) Close-up Cam | Show! MusicCore |MBC231111방","contents":"3:35","link":"https://tv.naver.com/v/42767271","retrieved":1699866865934,"image":"https://phinf.pstatic.net/tvcast/20231113_4/8igqu_1699866394224eovzu_JPEG/clip_20231113154853_16.jpg?type=f194_109_blend"},{"title":"[#최애직캠] Stray Kids I.N - LALALALA(스트레이 키즈 아이엔 - 락(樂)) Close-up Cam | Show! MusicCore | MBC231111방송","contents":"4:12","link":"https://tv.naver.com/v/42765689","retrieved":1699866865937,"image":"https://phinf.pstatic.net/tvcast/20231113_157/ErhPn_1699864892898wwlSq_JPEG/clip_20231113154902_18.jpg?type=f194_109_blend"},{"title":"[#최애직캠] Stray Kids FELIX - LALALALA(스트레이 키즈 필릭스 - 락(樂)) Close-up Cam | Show! MusicCore | MBC231111방","contents":"3:59","link":"https://tv.naver.com/v/42765688","retrieved":1699866865942,"image":"https://phinf.pstatic.net/tvcast/20231113_96/hIU2s_16998648911075XPe6_JPEG/clip_20231113154857_17.jpg?type=f194_109_blend"},{"title":"[#최애직캠] Stray Kids LEE KNOW - LALALALA(스트레이 키즈 리노 - 락(樂)) Close-up Cam | Show! MusicCore|MBC231111방","contents":"3:16","link":"https://tv.naver.com/v/42765391","retrieved":1699866865943,"image":"https://phinf.pstatic.net/tvcast/20231113_145/IMTgO_1699864591211QEyt5_JPEG/clip_20231113154841_15.jpg?type=f194_109_blend"},{"title":"[#최애직캠]ZEROBASEONE PARK GUN WOOK - MELTING POINT(제로베이스원 박건욱-멜팅 포인트)Close-upCam|MusicCore|MBC231111방","contents":"3:19","link":"https://tv.naver.com/v/42763726","retrieved":1699863501417,"image":"https://phinf.pstatic.net/tvcast/20231113_288/dGflV_1699863151244njFjp_JPEG/clip_20231113145640_8.jpg?type=f194_109_blend"},{"title":"[#최애직캠] ZEROBASEONE SEOK MATTHEW - MELTING POINT(제로베이스원 석매튜-멜팅 포인트)Close-upCam|MusicCore|MBC231111방","contents":"3:13","link":"https://tv.naver.com/v/42762251","retrieved":1699863501417,"image":"https://phinf.pstatic.net/tvcast/20231113_185/oXzB9_16998618954903OnC5_JPEG/clip_20231113145635_7.jpg?type=f194_109_blend"},{"title":"[예능연구소] ZEROBASEONE HAN YU JIN - MELTING POINT(제로베이스원 한유진 - 멜팅 포인트)FanCam|Show!MusicCore|MBC231111방","contents":"3:13","link":"https://tv.naver.com/v/42762246","retrieved":1699863501430,"image":"https://phinf.pstatic.net/tvcast/20231113_158/czInB_1699861894297kyz2I_JPEG/clip_20231113145629_6.jpg?type=f194_109_blend"},{"title":"[예능연구소] ZEROBASEONE Zhang Hao - MELTING POINT(제로베이스원 장하오 - 멜팅 포인트) FanCam|Show!MusicCore|MBC231111방","contents":"3:11","link":"https://tv.naver.com/v/42762241","retrieved":1699863501441,"image":"https://phinf.pstatic.net/tvcast/20231113_21/ojWvg_1699861892891Rsv5r_JPEG/clip_20231113145620_5.jpg?type=f194_109_blend"},{"title":"[예능연구소] ZEROBASEONE SUNG HAN BIN - MELTING POINT(제로베이스원 성한빈-멜팅 포인트)FanCam|Show!MusicCore|MBC231111방","contents":"3:21","link":"https://tv.naver.com/v/42762238","retrieved":1699863501448,"image":"https://phinf.pstatic.net/tvcast/20231113_213/VEXOe_1699861891629nIWNj_JPEG/clip_20231113145613_4.jpg?type=f194_109_blend"},{"title":"[예능연구소] NiziU RIKU – HEARTRIS(니쥬 리쿠 - 하트리스) FanCam | Show! MusicCore | MBC231111방송","contents":"3:21","link":"https://tv.naver.com/v/42689977","retrieved":1699705351276,"image":"https://phinf.pstatic.net/tvcast/20231111_36/ibWi3_1699701992918JKeUE_JPEG/clip_20231111194006_84.jpg?type=f194_109_blend"},{"title":"[예능연구소] KISS OF LIFE – Bad News(키스오브라이프 - 배드 뉴스) FanCam | Show! MusicCore | MBC231111방송","contents":"2:55","link":"https://tv.naver.com/v/42689785","retrieved":1699705351277,"image":"https://phinf.pstatic.net/tvcast/20231111_210/orgEm_16997016904503zYXs_JPEG/clip_20231111194206_86.jpg?type=f194_109_blend"},{"title":"[예능연구소] WHIB – BANG!(휘브 - 뱅!) FanCam | Show! MusicCore | MBC231111방송","contents":"3:01","link":"https://tv.naver.com/v/42689660","retrieved":1699705351277,"image":"https://phinf.pstatic.net/tvcast/20231111_32/ihqEt_1699701391276JMPx4_JPEG/clip_20231111194242_91.jpg?type=f194_109_blend"},{"title":"[예능연구소] KISS OF LIFE JULIE - Bad News(키스오브라이프 쥴리 - 배드 뉴스) FanCam | Show! MusicCore | MBC231111방송","contents":"2:56","link":"https://tv.naver.com/v/42689659","retrieved":1699705351277,"image":"https://phinf.pstatic.net/tvcast/20231111_213/dej2y_1699701390013vfHyz_JPEG/clip_20231111194214_87.jpg?type=f194_109_blend"},{"title":"[예능연구소] NiziU MIIHI – HEARTRIS(니쥬 미이히 - 하트리스) FanCam | Show! MusicCore | MBC231111방송","contents":"3:14","link":"https://tv.naver.com/v/42689550","retrieved":1699705351279,"image":"https://phinf.pstatic.net/tvcast/20231111_4/3G4lv_1699701150984UldI5_JPEG/clip_20231111194031_85.jpg?type=f194_109_blend"},{"title":"[예능연구소] NiziU - HEARTRIS(니쥬 – 하트리스) FanCam | Show! MusicCore | MBC231111방송","contents":"3:11","link":"https://tv.naver.com/v/42689523","retrieved":1699705351279,"image":"https://phinf.pstatic.net/tvcast/20231111_17/QFPDN_16997010952956O9ql_JPEG/clip_20231111193853_83.jpg?type=f194_109_blend"},{"title":"[예능연구소] YOUNGJAE - Do It(영재 – 두 잇) FanCam (Horizontal Ver.) | Show! MusicCore | MBC231111방송","contents":"3:20","link":"https://tv.naver.com/v/42689522","retrieved":1699705351281,"image":"https://phinf.pstatic.net/tvcast/20231111_213/8ZBuB_1699701093648M6zlg_JPEG/clip_20231111193741_82.jpg?type=f194_109_blend"},{"title":"[예능연구소] VIVIZ - MANIAC(비비지 – 매니악) FanCam | Show! MusicCore | MBC231111방송","contents":"3:27","link":"https://tv.naver.com/v/42689521","retrieved":1699705351281,"image":"https://phinf.pstatic.net/tvcast/20231111_18/QUWRc_1699701092047pQx7w_JPEG/clip_20231111193655_80.jpg?type=f194_109_blend"},{"title":"[예능연구소] TAEMIN - Guilty(태민 – 길티) FanCam (Horizontal Ver.) | Show! MusicCore | MBC231111방송","contents":"3:40","link":"https://tv.naver.com/v/42689519","retrieved":1699705351282,"image":"https://phinf.pstatic.net/tvcast/20231111_80/AsLrv_16997010900088wnWD_JPEG/clip_20231111193015_74.jpg?type=f194_109_blend"},{"title":"[예능연구소] VIVIZ EUNHA – MANIAC(비비지 은하 - 매니악) FanCam | Show! MusicCore | MBC231111방송","contents":"3:34","link":"https://tv.naver.com/v/42689373","retrieved":1699701012170,"image":"https://phinf.pstatic.net/tvcast/20231111_211/fGTzC_1699700795601IdCQL_JPEG/clip_20231111193704_81.jpg?type=f194_109_blend"},{"title":"[예능연구소] ZEROBASEONE – MELTING POINT(제로베이스원 - 멜팅 포인트) FanCam | Show! MusicCore | MBC231111방송","contents":"3:06","link":"https://tv.naver.com/v/42689372","retrieved":1699701012179,"image":"https://phinf.pstatic.net/tvcast/20231111_250/3QUON_1699700794219L31Tu_JPEG/clip_20231111193446_79.jpg?type=f194_109_blend"},{"title":"[예능연구소] TAEMIN – Guilty(태민 - 길티) FanCam | Show! MusicCore | MBC231111방송","contents":"3:40","link":"https://tv.naver.com/v/42689370","retrieved":1699701012187,"image":"https://phinf.pstatic.net/tvcast/20231111_147/ZxG9o_1699700793106bwtvy_JPEG/clip_20231111193026_75.jpg?type=f194_109_blend"}]}